MoreCustomTkinterWidgets/AnimatedImage.py
MoreCustomTkinterWidgets/AskDialog.py
MoreCustomTkinterWidgets/AskValue.py
MoreCustomTkinterWidgets/BetterCTkImage.py
MoreCustomTkinterWidgets/DateSelector.py
MoreCustomTkinterWidgets/FileExplorer.py
MoreCustomTkinterWidgets/Message.py
MoreCustomTkinterWidgets/Selector.py
MoreCustomTkinterWidgets/Separator.py
MoreCustomTkinterWidgets/SmoothFrame.py
MoreCustomTkinterWidgets/__init__.py
MoreCustomTkinterWidgets/Images/back_arrow_dark.png
MoreCustomTkinterWidgets/Images/back_arrow_light.png
MoreCustomTkinterWidgets/Images/error.png
MoreCustomTkinterWidgets/Images/file_dark.png
MoreCustomTkinterWidgets/Images/file_light.png
MoreCustomTkinterWidgets/Images/folder_dark.png
MoreCustomTkinterWidgets/Images/folder_light.png
MoreCustomTkinterWidgets/Images/forward_arrow_dark.png
MoreCustomTkinterWidgets/Images/forward_arrow_light.png
MoreCustomTkinterWidgets/Images/info.png
MoreCustomTkinterWidgets/Images/new_folder_dark.png
MoreCustomTkinterWidgets/Images/new_folder_light.png
MoreCustomTkinterWidgets/Images/warning.png
morecustomtkinterwidgets-5.2.0.dist-info/licenses/LICENSE
morecustomtkinterwidgets-5.2.0.dist-info/METADATA
morecustomtkinterwidgets-5.2.0.dist-info/WHEEL
morecustomtkinterwidgets-5.2.0.dist-info/top_level.txt
morecustomtkinterwidgets-5.2.0.dist-info/RECORD
