Metadata-Version: 2.4
Name: MoreCustomTkinterWidgets
Version: 5.2.0
Summary: A package containing more widgets for customtkinter
Author: Fastattack
License: MIT License
Project-URL: Homepage, https://github.com/fastattackv/MoreCustomTkinterWidgets
Project-URL: Issues, https://github.com/fastattackv/MoreCustomTkinterWidgets/issues
Classifier: Programming Language :: Python :: 3
Classifier: License :: OSI Approved :: MIT License
Classifier: Operating System :: OS Independent
Requires-Python: >=3.7
License-File: LICENSE
Requires-Dist: customtkinter>=5.2.1
Requires-Dist: Pillow>=9.5.0
Dynamic: license-file
